mssql_python/__init__.py
mssql_python/auth.py
mssql_python/connection.py
mssql_python/connection_string_builder.py
mssql_python/connection_string_parser.py
mssql_python/constants.py
mssql_python/cursor.py
mssql_python/db_connection.py
mssql_python/ddbc_bindings.cp310-arm64.so
mssql_python/ddbc_bindings.cp311-arm64.so
mssql_python/ddbc_bindings.cp312-arm64.so
mssql_python/ddbc_bindings.cp313-arm64.so
mssql_python/ddbc_bindings.cp314-arm64.so
mssql_python/ddbc_bindings.py
mssql_python/exceptions.py
mssql_python/helpers.py
mssql_python/logging.py
mssql_python/mssql_python.pyi
mssql_python/parameter_helper.py
mssql_python/pooling.py
mssql_python/row.py
mssql_python/type.py
mssql_python/libs/LICENSING
mssql_python/libs/linux/alpine/arm64/lib/MICROSOFT_ODBC_DRIVER_FOR_SQL_SERVER_LICENSE.txt
mssql_python/libs/linux/alpine/arm64/lib/libmsodbcsql-18.5.so.1.1
mssql_python/libs/linux/alpine/arm64/lib/libodbcinst.so.2
mssql_python/libs/linux/alpine/arm64/share/resources/en_US/msodbcsqlr18.rll
mssql_python/libs/linux/alpine/x86_64/lib/MICROSOFT_ODBC_DRIVER_FOR_SQL_SERVER_LICENSE.txt
mssql_python/libs/linux/alpine/x86_64/lib/libmsodbcsql-18.5.so.1.1
mssql_python/libs/linux/alpine/x86_64/lib/libodbcinst.so.2
mssql_python/libs/linux/alpine/x86_64/share/resources/en_US/msodbcsqlr18.rll
mssql_python/libs/linux/debian_ubuntu/arm64/lib/MICROSOFT_ODBC_DRIVER_FOR_SQL_SERVER_LICENSE.txt
mssql_python/libs/linux/debian_ubuntu/arm64/lib/libmsodbcsql-18.5.so.1.1
mssql_python/libs/linux/debian_ubuntu/arm64/lib/libodbcinst.so.2
mssql_python/libs/linux/debian_ubuntu/arm64/share/resources/en_US/msodbcsqlr18.rll
mssql_python/libs/linux/debian_ubuntu/x86_64/lib/MICROSOFT_ODBC_DRIVER_FOR_SQL_SERVER_LICENSE.txt
mssql_python/libs/linux/debian_ubuntu/x86_64/lib/libmsodbcsql-18.5.so.1.1
mssql_python/libs/linux/debian_ubuntu/x86_64/lib/libodbcinst.so.2
mssql_python/libs/linux/debian_ubuntu/x86_64/share/resources/en_US/msodbcsqlr18.rll
mssql_python-1.3.0.dist-info/licenses/LICENSE
mssql_python-1.3.0.dist-info/METADATA
mssql_python-1.3.0.dist-info/WHEEL
mssql_python-1.3.0.dist-info/top_level.txt
mssql_python-1.3.0.dist-info/RECORD
