Metadata-Version: 2.4
Name: mssql-python
Version: 1.3.0
Summary: A Python library for interacting with Microsoft SQL Server
Home-page: https://github.com/microsoft/mssql-python
Author: Microsoft Corporation
Author-email: mssql-python@microsoft.com
Classifier: Operating System :: Microsoft :: Windows
Classifier: Operating System :: MacOS
Classifier: Operating System :: POSIX :: Linux
Requires-Python: >=3.10
License-File: LICENSE
Requires-Dist: azure-identity>=1.12.0
Dynamic: author
Dynamic: author-email
Dynamic: classifier
Dynamic: description
Dynamic: description-content-type
Dynamic: home-page
Dynamic: license-file
Dynamic: requires-dist
Dynamic: requires-python
Dynamic: summary
